odoo8_addon_l10n_br_account-8.0.2.0.0-py2.7-nspkg.pth
odoo_addons/l10n_br_account/l10n_br_account_workflow.xml
odoo_addons/l10n_br_account/__openerp__.py
odoo_addons/l10n_br_account/__init__.py
odoo_addons/l10n_br_account/README.rst
odoo_addons/l10n_br_account/account_fiscal_position_workflow.xml
odoo_addons/l10n_br_account/account_invoice_workflow.xml
odoo_addons/l10n_br_account/security/l10n_br_account_security.xml
odoo_addons/l10n_br_account/security/ir.model.access.csv
odoo_addons/l10n_br_account/report/account_invoice_report_view.xml
odoo_addons/l10n_br_account/report/account_invoice_report.py
odoo_addons/l10n_br_account/report/__init__.py
odoo_addons/l10n_br_account/migrations/8.0.1.0.1/openupgrade_analysis_work.txt
odoo_addons/l10n_br_account/migrations/8.0.1.0.1/openupgrade_analysis.txt
odoo_addons/l10n_br_account/models/account_move_line.py
odoo_addons/l10n_br_account/models/res_config.py
odoo_addons/l10n_br_account/models/product.py
odoo_addons/l10n_br_account/models/account_fiscal_position_rule.py
odoo_addons/l10n_br_account/models/res_partner.py
odoo_addons/l10n_br_account/models/account_invoice.py
odoo_addons/l10n_br_account/models/l10n_br_account.py
odoo_addons/l10n_br_account/models/account.py
odoo_addons/l10n_br_account/models/__init__.py
odoo_addons/l10n_br_account/models/res_company.py
odoo_addons/l10n_br_account/i18n/pt_BR.po
odoo_addons/l10n_br_account/test/account_supplier_invoice.yml
odoo_addons/l10n_br_account/test/account_customer_invoice.yml
odoo_addons/l10n_br_account/test/generate_fiscal_rules.yml
odoo_addons/l10n_br_account/sped/__init__.py
odoo_addons/l10n_br_account/sped/document.py
odoo_addons/l10n_br_account/sped/ibpt/deolhonoimposto.py
odoo_addons/l10n_br_account/sped/ibpt/__init__.py
odoo_addons/l10n_br_account/views/l10n_br_account_view.xml
odoo_addons/l10n_br_account/views/res_partner_view.xml
odoo_addons/l10n_br_account/views/account_fiscal_position_rule_view.xml
odoo8_addon_l10n_br_account-8.0.2.0.0.dist-info/top_level.txt
odoo8_addon_l10n_br_account-8.0.2.0.0.dist-info/WHEEL
odoo8_addon_l10n_br_account-8.0.2.0.0.dist-info/RECORD
odoo8_addon_l10n_br_account-8.0.2.0.0.dist-info/metadata.json
odoo8_addon_l10n_br_account-8.0.2.0.0.dist-info/DESCRIPTION.rst
odoo8_addon_l10n_br_account-8.0.2.0.0.dist-info/METADATA
odoo8_addon_l10n_br_account-8.0.2.0.0.dist-info/namespace_packages.txt
