Metadata-Version: 2.0
Name: odoo8-addon-l10n-br-account
Version: 8.0.2.0.0
Summary: Brazilian Localization Account
Home-page: http://odoobrasil.org
Author: Akretion, Odoo Community Association (OCA)
Author-email: support@odoo-community.org
License: AGPL-3
Platform: UNKNOWN
Requires-Dist: odoo (<9.0a,>=8.0a)
Requires-Dist: odoo8-addon-account-fiscal-position-rule
Requires-Dist: odoo8-addon-l10n-br-base
Requires-Dist: odoo8-addon-web-context-tunnel
Classifier: Programming Language :: Python :: 2.7
Classifier: Framework :: Odoo
Classifier: License :: OSI Approved :: GNU Affero General Public License v3
